paar_dev/__init__.py
paar_dev/core.py
paar_dev-1.0.0.dist-info/METADATA
paar_dev-1.0.0.dist-info/WHEEL
paar_dev-1.0.0.dist-info/top_level.txt
paar_dev-1.0.0.dist-info/RECORD
