Metadata-Version: 2.4
Name: paar-dev
Version: 1.0.0
Summary: Biblioteca com funções específicas da Paar Desenvolvimentos
Author-email: Paar Desenvolvimentos <paardesenvolvimentos@gmail.com>
License: MIT
Requires-Python: >=3.8
